UART/uart_rx.v
module uart_rx (
    input  wire       clk,
    input  wire       rst,
    input  wire        tick,
    input  wire        RX,
    output reg  [7:0]  rx_data,
    output reg          rx_valid,
    output reg          rx_error
);

    // Stage 1: 2-flop synchronizer for the asynchronous RX input
    reg rx_sync1, rx_sync2;
    always @(posedge clk) begin
        if (rst) begin
            rx_sync1 <= 1'b1;
            rx_sync2 <= 1'b1;
        end else begin
            rx_sync1 <= RX;
            rx_sync2 <= rx_sync1;
        end
    end

    localparam IDLE  = 2'd0;
    localparam START = 2'd1;
    localparam DATA  = 2'd2;
    localparam STOP  = 2'd3;

    reg [1:0] state;
    reg [3:0] tick_cnt;
    reg [2:0] bit_cnt;
    reg [7:0] shift_reg;

    always @(posedge clk) begin
        if (rst) begin
            state    <= IDLE;
            tick_cnt <= 4'd0;
            bit_cnt  <= 3'd0;
            rx_data  <= 8'd0;
            rx_valid <= 1'b0;
            rx_error <= 1'b0;
        end else begin
            case (state)

                IDLE: begin
                    rx_valid <= 1'b0;
                    rx_error <= 1'b0;
                    if (rx_sync2 == 1'b0) begin
                        state    <= START;
                        tick_cnt <= 4'd0;
                    end
                end

                START: begin
                    if (tick) begin
                        if (tick_cnt == 4'd7) begin
                            if (rx_sync2 == 1'b1) begin
                                // glitch, not a real start bit - abort now
                                state <= IDLE;
                            end
                            // else: confirmed real start bit - fall through,
                            // keep counting to the end of this bit period below
                        end

                        if (tick_cnt == 4'd15) begin
                            // full 16-tick start-bit period has elapsed
                            tick_cnt <= 4'd0;
                            bit_cnt  <= 3'd0;
                            state    <= DATA;
                        end else begin
                            tick_cnt <= tick_cnt + 1'b1;
                        end
                    end
                end

                DATA: begin
                    if (tick) begin
                        if (tick_cnt == 4'd7) begin
                            shift_reg[bit_cnt] <= rx_sync2;
                        end
                        if (tick_cnt == 4'd15) begin
                            tick_cnt <= 4'd0;
                            if (bit_cnt == 3'd7) begin
                                state <= STOP;
                            end else begin
                                bit_cnt <= bit_cnt + 1'b1;
                            end
                        end else begin
                            tick_cnt <= tick_cnt + 1'b1;
                        end
                    end
                end

                STOP: begin
                    if (tick) begin
                        if (tick_cnt == 4'd7) begin
                            if (rx_sync2 == 1'b1) begin
                                rx_data  <= shift_reg;
                                rx_valid <= 1'b1;
                                rx_error <= 1'b0;
                            end else begin
                                rx_valid <= 1'b0;
                                rx_error <= 1'b1;
                            end
                        end
                        if (tick_cnt == 4'd15) begin
                            tick_cnt <= 4'd0;
                            state    <= IDLE;
                        end else begin
                            tick_cnt <= tick_cnt + 1'b1;
                        end
                    end
                end

                default: state <= IDLE;

            endcase
        end
    end

endmodule

UART/uart_tx.v
module uart_tx (
    input  wire       clk,
    input  wire       rst,
    input  wire        tick,
    input  wire        tx_start,
    input  wire [7:0]  tx_data,
    output reg         tx_busy,
    output reg         TX
);

    localparam IDLE  = 2'd0;
    localparam START = 2'd1;
    localparam DATA  = 2'd2;
    localparam STOP  = 2'd3;

    reg [1:0] state;
    reg [3:0] tick_cnt;
    reg [2:0] bit_cnt;
    reg [7:0] shift_reg;

    always @(posedge clk) begin
        if (rst) begin
            state    <= IDLE;
            TX       <= 1'b1;
            tx_busy  <= 1'b0;
            tick_cnt <= 4'd0;
            bit_cnt  <= 3'd0;
        end else begin
            case (state)

                IDLE: begin
                    TX <= 1'b1;
                    if (tx_start) begin
                        shift_reg <= tx_data;
                        tx_busy   <= 1'b1;
                        tick_cnt  <= 4'd0;
                        state     <= START;
                    end else begin
                        tx_busy <= 1'b0;
                    end
                end

                START: begin
                    TX <= 1'b0;
                    if (tick) begin
                        if (tick_cnt == 4'd15) begin
                            tick_cnt <= 4'd0;
                            bit_cnt  <= 3'd0;
                            state    <= DATA;
                        end else begin
                            tick_cnt <= tick_cnt + 1'b1;
                        end
                    end
                end

                DATA: begin
                    TX <= shift_reg[0];
                    if (tick) begin
                        if (tick_cnt == 4'd15) begin
                            tick_cnt  <= 4'd0;
                            shift_reg <= shift_reg >> 1;
                            if (bit_cnt == 3'd7) begin
                                state <= STOP;
                            end else begin
                                bit_cnt <= bit_cnt + 1'b1;
                            end
                        end else begin
                            tick_cnt <= tick_cnt + 1'b1;
                        end
                    end
                end

                STOP: begin
                    TX <= 1'b1;
                    if (tick) begin
                        if (tick_cnt == 4'd15) begin
                            tick_cnt <= 4'd0;
                            tx_busy  <= 1'b0;
                            state    <= IDLE;
                        end else begin
                            tick_cnt <= tick_cnt + 1'b1;
                        end
                    end
                end

                default: state <= IDLE;

            endcase
        end
    end

endmodule

UART/string_sender.v
module string_sender (
    input  wire        clk,
    input  wire        rst,
    input  wire         tx_busy,
    output reg          tx_start,
    output reg  [7:0]   tx_data
);

    localparam MSG_LEN = 18;

    reg [7:0] message [0:MSG_LEN-1];
    reg [4:0] index;

    initial begin
        message[0]  = "S";
        message[1]  = "I";
        message[2]  = "L";
        message[3]  = "I";
        message[4]  = "C";
        message[5]  = "O";
        message[6]  = "N";
        message[7]  = " ";
        message[8]  = "C";
        message[9]  = "R";
        message[10] = "A";
        message[11] = "F";
        message[12] = "T";
        message[13] = " ";
        message[14] = "V";
        message[15] = "L";
        message[16] = "S";
        message[17] = "I";
    end

    localparam S_IDLE      = 3'd0;
    localparam S_ASSERT    = 3'd1;
    localparam S_WAIT_BUSY = 3'd2;
    localparam S_WAIT_DONE = 3'd3;
    localparam S_NEXT      = 3'd4;
    localparam S_DONE      = 3'd5;

    reg [2:0] state;

    always @(posedge clk) begin
        if (rst) begin
            state    <= S_IDLE;
            index    <= 5'd0;
            tx_start <= 1'b0;
            tx_data  <= 8'd0;
        end else begin
            case (state)

                S_IDLE: begin
                    index    <= 5'd0;
                    tx_start <= 1'b0;
                    state    <= S_ASSERT;
                end

                S_ASSERT: begin
                    tx_data  <= message[index];
                    tx_start <= 1'b1;
                    state    <= S_WAIT_BUSY;
                end

                S_WAIT_BUSY: begin
                    tx_start <= 1'b0;
                    if (tx_busy)
                        state <= S_WAIT_DONE;
                end

                S_WAIT_DONE: begin
                    if (!tx_busy)
                        state <= S_NEXT;
                end

                S_NEXT: begin
                    if (index == MSG_LEN - 1)
                        state <= S_DONE;
                    else begin
                        index <= index + 1'b1;
                        state <= S_ASSERT;
                    end
                end

                S_DONE: begin
                    tx_start <= 1'b0;
                end

                default: state <= S_IDLE;

            endcase
        end
    end

endmodule

UART/baud_gen.v
module baud_gen (
    input  wire clk,
    input  wire rst,
    output reg  tick
);

    parameter CLK_FREQ  = 50_000_000;
    parameter BAUD_RATE  = 115200;
    localparam DIVISOR  = CLK_FREQ / (BAUD_RATE * 16);

    reg [15:0] counter;

    always @(posedge clk) begin
        if (rst) begin
            counter <= 16'd0;
            tick    <= 1'b0;
        end else if (counter == DIVISOR - 1) begin
            counter <= 16'd0;
            tick    <= 1'b1;
        end else begin
            counter <= counter + 1'b1;
            tick    <= 1'b0;
        end
    end

endmodule

UART/uart_top.v
module uart_top (
    input  wire        clk,
    input  wire        rst,
    output wire         TX,
    input  wire         RX,
    output wire [7:0]  rx_data,
    output wire         rx_valid,
    output wire         rx_error
);

    wire       tick;
    wire       tx_busy;
    wire       tx_start;
    wire [7:0] tx_data;

    baud_gen #(
        .CLK_FREQ  (50_000_000),
        .BAUD_RATE (115200)
    ) baud_gen_inst (
        .clk  (clk),
        .rst  (rst),
        .tick (tick)
    );

    string_sender string_sender_inst (
        .clk      (clk),
        .rst      (rst),
        .tx_busy  (tx_busy),
        .tx_start (tx_start),
        .tx_data  (tx_data)
    );

    uart_tx uart_tx_inst (
        .clk      (clk),
        .rst      (rst),
        .tick     (tick),
        .tx_start (tx_start),
        .tx_data  (tx_data),
        .tx_busy  (tx_busy),
        .TX       (TX)
    );

    uart_rx uart_rx_inst (
        .clk      (clk),
        .rst      (rst),
        .tick     (tick),
        .RX       (RX),
        .rx_data  (rx_data),
        .rx_valid (rx_valid),
        .rx_error (rx_error)
    );

endmodule

UART/tb_uart_top.v
`timescale 1ns/1ps

module tb_uart_top;

    reg  clk;
    reg  rst;
    wire TX;
    wire [7:0] rx_data;
    wire       rx_valid;
    wire       rx_error;

    localparam CLK_FREQ  = 50_000_000;
    localparam BAUD_RATE  = 115200;
    localparam DIVISOR   = CLK_FREQ / (BAUD_RATE * 16);
    localparam CLK_PERIOD_NS = 20;
    localparam MSG_LEN   = 18;

    localparam CLKS_PER_FRAME = 10 * 16 * DIVISOR;
    localparam NS_PER_FRAME   = CLKS_PER_FRAME * CLK_PERIOD_NS;
    localparam SIM_TIMEOUT_NS = (MSG_LEN * NS_PER_FRAME) + 5000;

    reg [7:0] expected [0:MSG_LEN-1];
    integer   rx_index;
    integer   pass_count = 0;
    integer   fail_count = 0;

    uart_top dut (
        .clk      (clk),
        .rst      (rst),
        .TX       (TX),
        .RX       (TX),
        .rx_data  (rx_data),
        .rx_valid (rx_valid),
        .rx_error (rx_error)
    );

    always #(CLK_PERIOD_NS/2) clk = ~clk;

    // ---- Waveform dump setup ----
    initial begin
        $dumpfile("tb_uart_top.vcd");
        $dumpvars(0, tb_uart_top);   // dump all signals in this module and below (DUT included)
    end

    initial begin
        expected[0]  = "S"; expected[1]  = "I"; expected[2]  = "L";
        expected[3]  = "I"; expected[4]  = "C"; expected[5]  = "O";
        expected[6]  = "N"; expected[7]  = " "; expected[8]  = "C";
        expected[9]  = "R"; expected[10] = "A"; expected[11] = "F";
        expected[12] = "T"; expected[13] = " "; expected[14] = "V";
        expected[15] = "L"; expected[16] = "S"; expected[17] = "I";
    end

    initial begin
        clk      = 0;
        rst      = 1;
        rx_index = 0;
        #50 rst = 0;
        $display("Computed SIM_TIMEOUT_NS = %0d ns (DIVISOR=%0d, %0d clocks/frame)",
                   SIM_TIMEOUT_NS, DIVISOR, CLKS_PER_FRAME);
    end

    always @(posedge clk) begin
        if (rx_valid) begin
            if (rx_index < MSG_LEN) begin
                if (rx_data !== expected[rx_index]) begin
                    $display("FAIL: char %0d expected '%c' (0x%0h), got '%c' (0x%0h)",
                              rx_index, expected[rx_index], expected[rx_index],
                              rx_data, rx_data);
                    fail_count = fail_count + 1;
                end else begin
                    $display("PASS: char %0d = '%c' received correctly", rx_index, rx_data);
                    pass_count = pass_count + 1;
                end
                rx_index = rx_index + 1;
            end else begin
                $display("FAIL: received more characters than expected (index %0d)", rx_index);
                fail_count = fail_count + 1;
                rx_index = rx_index + 1;
            end
        end

        if (rx_error) begin
            $display("FAIL: rx_error asserted unexpectedly at char %0d", rx_index);
            fail_count = fail_count + 1;
        end
    end

    initial begin
        #(50 + SIM_TIMEOUT_NS);
        if (rx_index !== MSG_LEN) begin
            $display("FAIL: only received %0d of %0d expected characters", rx_index, MSG_LEN);
            fail_count = fail_count + 1;
        end
        $display("---------------------------------------------");
        $display("TESTS PASSED: %0d   TESTS FAILED: %0d", pass_count, fail_count);
        $display("---------------------------------------------");
        $finish;
    end

endmodule

UART/tb_uart_top.vcd
$date
	Thu Sep 10 14:59:42 2026
$end
$version
	Icarus Verilog
$end
$timescale
	1ps
$end
$scope module tb_uart_top $end
$var wire 1 ! rx_valid $end
$var wire 1 " rx_error $end
$var wire 8 # rx_data [7:0] $end
$var wire 1 $ TX $end
$var parameter 32 % BAUD_RATE $end
$var parameter 128 & CLKS_PER_FRAME $end
$var parameter 32 ' CLK_FREQ $end
$var parameter 32 ( CLK_PERIOD_NS $end
$var parameter 64 ) DIVISOR $end
$var parameter 32 * MSG_LEN $end
$var parameter 160 + NS_PER_FRAME $end
$var parameter 193 , SIM_TIMEOUT_NS $end
$var reg 1 - clk $end
$var reg 1 . rst $end
$var integer 32 / fail_count [31:0] $end
$var integer 32 0 pass_count [31:0] $end
$var integer 32 1 rx_index [31:0] $end
$scope module dut $end
$var wire 1 - clk $end
$var wire 1 . rst $end
$var wire 1 2 tx_start $end
$var wire 8 3 tx_data [7:0] $end
$var wire 1 4 tx_busy $end
$var wire 1 5 tick $end
$var wire 1 ! rx_valid $end
$var wire 1 " rx_error $end
$var wire 8 6 rx_data [7:0] $end
$var wire 1 $ TX $end
$var wire 1 $ RX $end
$scope module baud_gen_inst $end
$var wire 1 - clk $end
$var wire 1 . rst $end
$var parameter 32 7 BAUD_RATE $end
$var parameter 32 8 CLK_FREQ $end
$var parameter 64 9 DIVISOR $end
$var reg 16 : counter [15:0] $end
$var reg 1 5 tick $end
$upscope $end
$scope module string_sender_inst $end
$var wire 1 - clk $end
$var wire 1 . rst $end
$var wire 1 4 tx_busy $end
$var parameter 32 ; MSG_LEN $end
$var parameter 3 < S_ASSERT $end
$var parameter 3 = S_DONE $end
$var parameter 3 > S_IDLE $end
$var parameter 3 ? S_NEXT $end
$var parameter 3 @ S_WAIT_BUSY $end
$var parameter 3 A S_WAIT_DONE $end
$var reg 5 B index [4:0] $end
$var reg 3 C state [2:0] $end
$var reg 8 D tx_data [7:0] $end
$var reg 1 2 tx_start $end
$upscope $end
$scope module uart_rx_inst $end
$var wire 1 - clk $end
$var wire 1 . rst $end
$var wire 1 5 tick $end
$var wire 1 $ RX $end
$var parameter 2 E DATA $end
$var parameter 2 F IDLE $end
$var parameter 2 G START $end
$var parameter 2 H STOP $end
$var reg 3 I bit_cnt [2:0] $end
$var reg 8 J rx_data [7:0] $end
$var reg 1 " rx_error $end
$var reg 1 K rx_sync1 $end
$var reg 1 L rx_sync2 $end
$var reg 1 ! rx_valid $end
$var reg 8 M shift_reg [7:0] $end
$var reg 2 N state [1:0] $end
$var reg 4 O tick_cnt [3:0] $end
$upscope $end
$scope module uart_tx_inst $end
$var wire 1 - clk $end
$var wire 1 . rst $end
$var wire 1 5 tick $end
$var wire 8 P tx_data [7:0] $end
$var wire 1 2 tx_start $end
$var parameter 2 Q DATA $end
$var parameter 2 R IDLE $end
$var parameter 2 S START $end
$var parameter 2 T STOP $end
$var reg 1 $ TX $end
$var reg 3 U bit_cnt [2:0] $end
$var reg 8 V shift_reg [7:0] $end
$var reg 2 W state [1:0] $end
$var reg 4 X tick_cnt [3:0] $end
$var reg 1 4 tx_busy $end
$upscope $end
$upscope $end
$upscope $end
$enddefinitions $end
$comment Show the parameter values. $end
$dumpall
b11 T
b1 S
b0 R
b10 Q
b11 H
b1 G
b0 F
b10 E
b11 A
b10 @
b100 ?
b0 >
b101 =
b1 <
b10010 ;
b11011 9
b10111110101111000010000000 8
b11100001000000000 7
b101111100111010001000 ,
b10101000110000000 +
b10010 *
b11011 )
b10100 (
b10111110101111000010000000 '
b1000011100000 &
b11100001000000000 %
$end
#0
$dumpvars
bx X
bx W
bx V
bx U
bx P
bx O
bx N
bx M
xL
xK
bx J
bx I
bx D
bx C
bx B
bx :
bx 6
x5
x4
bx 3
x2
b0 1
b0 0
b0 /
1.
0-
x$
bx #
x"
x!
$end
#10000
05
b0 :
b0 3
b0 D
b0 P
02
b0 B
b0 C
b0 U
b0 X
04
1$
b0 W
1L
1K
0"
0!
b0 #
b0 6
b0 J
b0 I
b0 O
b0 N
1-
#20000
0-
#30000
1-
#40000
0-
#50000
b1 :
b1 C
1-
0.
#60000
0-
#70000
b10 C
12
b1010011 3
b1010011 D
b1010011 P
b10 :
1-
#80000
0-
#90000
b11 :
02
b1 W
14
b1010011 V
1-
#100000
0-
#110000
0$
b11 C
b100 :
1-
#120000
0-
#130000
b101 :
0K
1-
#140000
0-
#150000
0L
b110 :
1-
#160000
0-
#170000
b111 :
b1 N
1-
#180000
0-
#190000
b1000 :
1-
#200000
0-
#210000
b1001 :
1-
#220000
0-
#230000
b1010 :
1-
#240000
0-
#250000
b1011 :
1-
#260000
0-
#270000
b1100 :
1-
#280000
0-
#290000
b1101 :
1-
#300000
0-
#310000
b1110 :
1-
#320000
0-
#330000
b1111 :
1-
#340000
0-
#350000
b10000 :
1-
#360000
0-
#370000
b10001 :
1-
#380000
0-
#390000
b10010 :
1-
#400000
0-
#410000
b10011 :
1-
#420000
0-
#430000
b10100 :
1-
#440000
0-
#450000
b10101 :
1-
#460000
0-
#470000
b10110 :
1-
#480000
0-
#490000
b10111 :
1-
#500000
0-
#510000
b11000 :
1-
#520000
0-
#530000
b11001 :
1-
#540000
0-
#550000
b11010 :
1-
#560000
0-
#570000
15
b0 :
1-
#580000
0-
#590000
b1 O
b1 X
05
b1 :
1-
#600000
0-
#610000
b10 :
1-
#620000
0-
#630000
b11 :
1-
#640000
0-
#650000
b100 :
1-
#660000
0-
#670000
b101 :
1-
#680000
0-
#690000
b110 :
1-
#700000
0-
#710000
b111 :
1-
#720000
0-
#730000
b1000 :
1-
#740000
0-
#750000
b1001 :
1-
#760000
0-
#770000
b1010 :
1-
#780000
0-
#790000
b1011 :
1-
#800000
0-
#810000
b1100 :
1-
#820000
0-
#830000
b1101 :
1-
#840000
0-
#850000
b1110 :
1-
#860000
0-
#870000
b1111 :
1-
#880000
0-
#890000
b10000 :
1-
#900000
0-
#910000
b10001 :
1-
#920000
0-
#930000
b10010 :
1-
#940000
0-
#950000
b10011 :
1-
#960000
0-
#970000
b10100 :
1-
#980000
0-
#990000
b10101 :
1-
#1000000
0-
#1010000
b10110 :
1-
#1020000
0-
#1030000
b10111 :
1-
#1040000
0-
#1050000
b11000 :
1-
#1060000
0-
#1070000
b11001 :
1-
#1080000
0-
#1090000
b11010 :
1-
#1100000
0-
#1110000
15
b0 :
1-
#1120000
0-
#1130000
05
b1 :
b10 X
b10 O
1-
#1140000
0-
#1150000
b10 :
1-
#1160000
0-
#1170000
b11 :
1-
#1180000
0-
#1190000
b100 :
1-
#1200000
0-
#1210000
b101 :
1-
#1220000
0-
#1230000
b110 :
1-
#1240000
0-
#1250000
b111 :
1-
#1260000
0-
#1270000
b1000 :
1-
#1280000
0-
#1290000
b1001 :
1-
#1300000
0-
#1310000
b1010 :
1-
#1320000
0-
#1330000
b1011 :
1-
#1340000
0-
#1350000
b1100 :
1-
#1360000
0-
#1370000
b1101 :
1-
#1380000
0-
#1390000
b1110 :
1-
#1400000
0-
#1410000
b1111 :
1-
#1420000
0-
#1430000
b10000 :
1-
#1440000
0-
#1450000
b10001 :
1-
#1460000
0-
#1470000
b10010 :
1-
#1480000
0-
#1490000
b10011 :
1-
#1500000
0-
#1510000
b10100 :
1-
#1520000
0-
#1530000
b10101 :
1-
#1540000
0-
#1550000
b10110 :
1-
#1560000
0-
#1570000
b10111 :
1-
#1580000
0-
#1590000
b11000 :
1-
#1600000
0-
#1610000
b11001 :
1-
#1620000
0-
#1630000
b11010 :
1-
#1640000
0-
#1650000
15
b0 :
1-
#1660000
0-
#1670000
b11 O
b11 X
05
b1 :
1-
#1680000
0-
#1690000
b10 :
1-
#1700000
0-
#1710000
b11 :
1-
#1720000
0-
#1730000
b100 :
1-
#1740000
0-
#1750000
b101 :
1-
#1760000
0-
#1770000
b110 :
1-
#1780000
0-
#1790000
b111 :
1-
#1800000
0-
#1810000
b1000 :
1-
#1820000
0-
#1830000
b1001 :
1-
#1840000
0-
#1850000
b1010 :
1-
#1860000
0-
#1870000
b1011 :
1-
#1880000
0-
#1890000
b1100 :
1-
#1900000
0-
#1910000
b1101 :
1-
#1920000
0-
#1930000
b1110 :
1-
#1940000
0-
#1950000
b1111 :
1-
#1960000
0-
#1970000
b10000 :
1-
#1980000
0-
#1990000
b10001 :
1-
#2000000
0-
#2010000
b10010 :
1-
#2020000
0-
#2030000
b10011 :
1-
#2040000
0-
#2050000
b10100 :
1-
#2060000
0-
#2070000
b10101 :
1-
#2080000
0-
#2090000
b10110 :
1-
#2100000
0-
#2110000
b10111 :
1-
#2120000
0-
#2130000
b11000 :
1-
#2140000
0-
#2150000
b11001 :
1-
#2160000
0-
#2170000
b11010 :
1-
#2180000
0-
#2190000
15
b0 :
1-
#2200000
0-
#2210000
05
b1 :
b100 X
b100 O
1-
#2220000
0-
#2230000
b10 :
1-
#2240000
0-
#2250000
b11 :
1-
#2260000
0-
#2270000
b100 :
1-
#2280000
0-
#2290000
b101 :
1-
#2300000
0-
#2310000
b110 :
1-
#2320000
0-
#2330000
b111 :
1-
#2340000
0-
#2350000
b1000 :
1-
#2360000
0-
#2370000
b1001 :
1-
#2380000
0-
#2390000
b1010 :
1-
#2400000
0-
#2410000
b1011 :
1-
#2420000
0-
#2430000
b1100 :
1-
#2440000
0-
#2450000
b1101 :
1-
#2460000
0-
#2470000
b1110 :
1-
#2480000
0-
#2490000
b1111 :
1-
#2500000
0-
#2510000
b10000 :
1-
#2520000
0-
#2530000
b10001 :
1-
#2540000
0-
#2550000
b10010 :
1-
#2560000
0-
#2570000
b10011 :
1-
#2580000
0-
#2590000
b10100 :
1-
#2600000
0-
#2610000
b10101 :
1-
#2620000
0-
#2630000
b10110 :
1-
#2640000
0-
#2650000
b10111 :
1-
#2660000
0-
#2670000
b11000 :
1-
#2680000
0-
#2690000
b11001 :
1-
#2700000
0-
#2710000
b11010 :
1-
#2720000
0-
#2730000
15
b0 :
1-
#2740000
0-
#2750000
b101 O
b101 X
05
b1 :
1-
#2760000
0-
#2770000
b10 :
1-
#2780000
0-
#2790000
b11 :
1-
#2800000
0-
#2810000
b100 :
1-
#2820000
0-
#2830000
b101 :
1-
#2840000
0-
#2850000
b110 :
1-
#2860000
0-
#2870000
b111 :
1-
#2880000
0-
#2890000
b1000 :
1-
#2900000
0-
#2910000
b1001 :
1-
#2920000
0-
#2930000
b1010 :
1-
#2940000
0-
#2950000
b1011 :
1-
#2960000
0-
#2970000
b1100 :
1-
#2980000
0-
#2990000
b1101 :
1-
#3000000
0-
#3010000
b1110 :
1-
#3020000
0-
#3030000
b1111 :
1-
#3040000
0-
#3050000
b10000 :
1-
#3060000
0-
#3070000
b10001 :
1-
#3080000
0-
#3090000
b10010 :
1-
#3100000
0-
#3110000
b10011 :
1-
#3120000
0-
#3130000
b10100 :
1-
#3140000
0-
#3150000
b10101 :
1-
#3160000
0-
#3170000
b10110 :
1-
#3180000
0-
#3190000
b10111 :
1-
#3200000
0-
#3210000
b11000 :
1-
#3220000
0-
#3230000
b11001 :
1-
#3240000
0-
#3250000
b11010 :
1-
#3260000
0-
#3270000
15
b0 :
1-
#3280000
0-
#3290000
05
b1 :
b110 X
b110 O
1-
#3300000
0-
#3310000
b10 :
1-
#3320000
0-
#3330000
b11 :
1-
#3340000
0-
#3350000
b100 :
1-
#3360000
0-
#3370000
b101 :
1-
#3380000
0-
#3390000
b110 :
1-
#3400000
0-
#3410000
b111 :
1-
#3420000
0-
#3430000
b1000 :
1-
#3440000
0-
#3450000
b1001 :
1-
#3460000
0-
#3470000
b1010 :
1-
#3480000
0-
#3490000
b1011 :
1-
#3500000
0-
#3510000
b1100 :
1-
#3520000
0-
#3530000
b1101 :
1-
#3540000
0-
#3550000
b1110 :
1-
#3560000
0-
#3570000
b1111 :
1-
#3580000
0-
#3590000
b10000 :
1-
#3600000
0-
#3610000
b10001 :
1-
#3620000
0-
#3630000
b10010 :
1-
#3640000
0-
#3650000
b10011 :
1-
#3660000
0-
#3670000
b10100 :
1-
#3680000
0-
#3690000
b10101 :
1-
#3700000
0-
#3710000
b10110 :
1-
#3720000
0-
#3730000
b10111 :
1-
#3740000
0-
#3750000
b11000 :
1-
#3760000
0-
#3770000
b11001 :
1-
#3780000
0-
#3790000
b11010 :
1-
#3800000
0-
#3810000
15
b0 :
1-
#3820000
0-
#3830000
b111 O
b111 X
05
b1 :
1-
#3840000
0-
#3850000
b10 :
1-
#3860000
0-
#3870000
b11 :
1-
#3880000
0-
#3890000
b100 :
1-
#3900000
0-
#3910000
b101 :
1-
#3920000
0-
#3930000
b110 :
1-
#3940000
0-
#3950000
b111 :
1-
#3960000
0-
#3970000
b1000 :
1-
#3980000
0-
#3990000
b1001 :
1-
#4000000
0-
#4010000
b1010 :
1-
#4020000
0-
#4030000
b1011 :
1-
#4040000
0-
#4050000
b1100 :
1-
#4060000
0-
#4070000
b1101 :
1-
#4080000
0-
#4090000
b1110 :
1-
#4100000
0-
#4110000
b1111 :
1-
#4120000
0-
#4130000
b10000 :
1-
#4140000
0-
#4150000
b10001 :
1-
#4160000
0-
#4170000
b10010 :
1-
#4180000
0-
#4190000
b10011 :
1-
#4200000
0-
#4210000
b10100 :
1-
#4220000
0-
#4230000
b10101 :
1-
#4240000
0-
#4250000
b10110 :
1-
#4260000
0-
#4270000
b10111 :
1-
#4280000
0-
#4290000
b11000 :
1-
#4300000
0-
#4310000
b11001 :
1-
#4320000
0-
#4330000
b11010 :
1-
#4340000
0-
#4350000
15
b0 :
1-
#4360000
0-
#4370000
05
b1 :
b1000 X
b1000 O
1-
#4380000
0-
#4390000
b10 :
1-
#4400000
0-
#4410000
b11 :
1-
#4420000
0-
#4430000
b100 :
1-
#4440000
0-
#4450000
b101 :
1-
#4460000
0-
#4470000
b110 :
1-
#4480000
0-
#4490000
b111 :
1-
#4500000
0-
#4510000
b1000 :
1-
#4520000
0-
#4530000
b1001 :
1-
#4540000
0-
#4550000
b1010 :
1-
#4560000
0-
#4570000
b1011 :
1-
#4580000
0-
#4590000
b1100 :
1-
#4600000
0-
#4610000
b1101 :
1-
#4620000
0-
#4630000
b1110 :
1-
#4640000
0-
#4650000
b1111 :
1-
#4660000
0-
#4670000
b10000 :
1-
#4680000
0-
#4690000
b10001 :
1-
#4700000
0-
#4710000
b10010 :
1-
#4720000
0-
#4730000
b10011 :
1-
#4740000
0-
#4750000
b10100 :
1-
#4760000
0-
#4770000
b10101 :
1-
#4780000
0-
#4790000
b10110 :
1-
#4800000
0-
#4810000
b10111 :
1-
#4820000
0-
#4830000
b11000 :
1-
#4840000
0-
#4850000
b11001 :
1-
#4860000
0-
#4870000
b11010 :
1-
#4880000
0-
#4890000
15
b0 :
1-
#4900000
0-
#4910000
b1001 O
b1001 X
05
b1 :
1-
#4920000
0-
#4930000
b10 :
1-
#4940000
0-
#4950000
b11 :
1-
#4960000
0-
#4970000
b100 :
1-
#4980000
0-
#4990000
b101 :
1-
#5000000
0-
#5010000
b110 :
1-
#5020000
0-
#5030000
b111 :
1-
#5040000
0-
#5050000
b1000 :
1-
#5060000
0-
#5070000
b1001 :
1-
#5080000
0-
#5090000
b1010 :
1-
#5100000
0-
#5110000
b1011 :
1-
#5120000
0-
#5130000
b1100 :
1-
#5140000
0-
#5150000
b1101 :
1-
#5160000
0-
#5170000
b1110 :
1-
#5180000
0-
#5190000
b1111 :
1-
#5200000
0-
#5210000
b10000 :
1-
#5220000
0-
#5230000
b10001 :
1-
#5240000
0-
#5250000
b10010 :
1-
#5260000
0-
#5270000
b10011 :
1-
#5280000
0-
#5290000
b10100 :
1-
#5300000
0-
#5310000
b10101 :
1-
#5320000
0-
#5330000
b10110 :
1-
#5340000
0-
#5350000
b10111 :
1-
#5360000
0-
#5370000
b11000 :
1-
#5380000
0-
#5390000
b11001 :
1-
#5400000
0-
#5410000
b11010 :
1-
#5420000
0-
#5430000
15
b0 :
1-
#5440000
0-
#5450000
05
b1 :
b1010 X
b1010 O
1-
#5460000
0-
#5470000
b10 :
1-
#5480000
0-
#5490000
b11 :
1-
#5500000
0-
#5510000
b100 :
1-
#5520000
0-
#5530000
b101 :
1-
#5540000
0-
#5550000
b110 :
1-
#5560000
0-
#5570000
b111 :
1-
#5580000
0-
#5590000
b1000 :
1-
#5600000
0-
#5610000
b1001 :
1-
#5620000
0-
#5630000
b1010 :
1-
#5640000
0-
#5650000
b1011 :
1-
#5660000
0-
#5670000
b1100 :
1-
#5680000
0-
#5690000
b1101 :
1-
#5700000
0-
#5710000
b1110 :
1-
#5720000
0-
#5730000
b1111 :
1-
#5740000
0-
#5750000
b10000 :
1-
#5760000
0-
#5770000
b10001 :
1-
#5780000
0-
#5790000
b10010 :
1-
#5800000
0-
#5810000
b10011 :
1-
#5820000
0-
#5830000
b10100 :
1-
#5840000
0-
#5850000
b10101 :
1-
#5860000
0-
#5870000
b10110 :
1-
#5880000
0-
#5890000
b10111 :
1-
#5900000
0-
#5910000
b11000 :
1-
#5920000
0-
#5930000
b11001 :
1-
#5940000
0-
#5950000
b11010 :
1-
#5960000
0-
#5970000
15
b0 :
1-
#5980000
0-
#5990000
b1011 O
b1011 X
05
b1 :
1-
#6000000
0-
#6010000
b10 :
1-
#6020000
0-
#6030000
b11 :
1-
#6040000
0-
#6050000
b100 :
1-
#6060000
0-
#6070000
b101 :
1-
#6080000
0-
#6090000
b110 :
1-
#6100000
0-
#6110000
b111 :
1-
#6120000
0-
#6130000
b1000 :
1-
#6140000
0-
#6150000
b1001 :
1-
#6160000
0-
#6170000
b1010 :
1-
#6180000
0-
#6190000
b1011 :
1-
#6200000
0-
#6210000
b1100 :
1-
#6220000
0-
#6230000
b1101 :
1-
#6240000
0-
#6250000
b1110 :
1-
#6260000
0-
#6270000
b1111 :
1-
#6280000
0-
#6290000
b10000 :
1-
#6300000
0-
#6310000
b10001 :
1-
#6320000
0-
#6330000
b10010 :
1-
#6340000
0-
#6350000
b10011 :
1-
#6360000
0-
#6370000
b10100 :
1-
#6380000
0-
#6390000
b10101 :
1-
#6400000
0-
#6410000
b10110 :
1-
#6420000
0-
#6430000
b10111 :
1-
#6440000
0-
#6450000
b11000 :
1-
#6460000
0-
#6470000
b11001 :
1-
#6480000
0-
#6490000
b11010 :
1-
#6500000
0-
#6510000
15
b0 :
1-
#6520000
0-
#6530000
05
b1 :
b1100 X
b1100 O
1-
#6540000
0-
#6550000
b10 :
1-
#6560000
0-
#6570000
b11 :
1-
#6580000
0-
#6590000
b100 :
1-
#6600000
0-
#6610000
b101 :
1-
#6620000
0-
#6630000
b110 :
1-
#6640000
0-
#6650000
b111 :
1-
#6660000
0-
#6670000
b1000 :
1-
#6680000
0-
#6690000
b1001 :
1-
#6700000
0-
#6710000
b1010 :
1-
#6720000
0-
#6730000
b1011 :
1-
#6740000
0-
#6750000
b1100 :
1-
#6760000
0-
#6770000
b1101 :
1-
#6780000
0-
